{
  "next": "",
  "list": [
    {
      "_id": 70,
      "type": "RU",
      "author": "001",
      "base": true,
      "preview": "/res/kls/RU/base.jpg",
      "kls": "/res/kls/RU/base.kls",
      "size": 75671,
      "name": "Волшебная клавиатура",
      "des": "Русская раскладка клавиатуры",
      "md5": "a7e00115f15b444493566ca3b5e0a1a4"
    },
    {
      "_id": 71,
      "type": "RU",
      "author": "002",
      "vip": true,
      "preview": "/res/kls/RU/gemstone.jpg",
      "kls": "/res/kls/RU/gemstone.kls",
      "size": 75395,
      "name": "Клавиатура с драгоценными камнями",
      "des": "Русская клавиатура из драгоценных камней",
      "md5": "709c47d703646b0be76f550f20db7d2f"
    },
    {
      "_id": 72,
      "type": "RU",
      "author": "002",
      "vip": true,
      "preview": "/res/kls/RU/jade.jpg",
      "kls": "/res/kls/RU/jade.kls",
      "size": 75356,
      "name": "Нефритовая клавиатура",
      "des": "Русская нефритовая клавиатура",
      "md5": "572da840af808701db3f0e41a30281ae"
    },
    {
      "_id": 73,
      "type": "RU",
      "author": "002",
      "vip": true,
      "preview": "/res/kls/RU/grass.jpg",
      "kls": "/res/kls/RU/grass.kls",
      "size": 75352,
      "name": "Травяная клавиатура",
      "des": "Русская травяная клавиатура",
      "md5": "39086b3de9d0ea21918dbbc97dd8aee0"
    },
    {
      "_id": 74,
      "type": "RU",
      "author": "002",
      "vip": true,
      "preview": "/res/kls/RU/fire.jpg",
      "kls": "/res/kls/RU/fire.kls",
      "size": 75527,
      "name": "Огненная клавиатура",
      "des": "Русская огненная клавиатура",
      "md5": "b9ccb001629c33c12a75268125f1d596"
    },
    {
      "_id": 75,
      "type": "RU",
      "author": "002",
      "vip": true,
      "preview": "/res/kls/RU/water.jpg",
      "kls": "/res/kls/RU/water.kls",
      "size": 130258,
      "name": "Водная клавиатура",
      "des": "Русская водная клавиатура",
      "md5": "d0b2f9fcaf5f1b4b89fbe4cb3a369043"
    },
    {
      "_id": 76,
      "type": "RU",
      "author": "002",
      "vip": true,
      "preview": "/res/kls/RU/bubbles.jpg",
      "kls": "/res/kls/RU/bubbles.kls",
      "size": 223490,
      "name": "Клавиатура Bubbles",
      "des": "Клавиатура Bubbles на русском языке",
      "md5": "806727760d3ac7ee52e3b8d09acade82"
    },
    {
      "_id": 77,
      "type": "RU",
      "author": "002",
      "vip": true,
      "preview": "/res/kls/RU/mechanical.jpg",
      "kls": "/res/kls/RU/mechanical.kls",
      "size": 218414,
      "name": "Механическая клавиатура",
      "des": "Русская механическая клавиатура",
      "md5": "f90db18406c9ee32ed86bba8ead05218"
    }
  ]
}
